{
  "chain": [
    {
      "phase": "DI_TitleCreation",
      "phaseType": "SimplePhase",
      "max_turn_step": -1,
      "need_reflect": "True"
    },
    {
      "phase": "DI_ResumeCreation",
      "phaseType": "SimplePhase",
      "max_turn_step": -1,
      "need_reflect": "True"
    }
  ],
  "recruitments": [
    "Instrutional Designer",
    "Project Mannager"
  ],
  "clear_structure": "True",
  "brainstorming": "False",
  "gui_design": "True",
  "git_management": "False",
  "self_improve": "False"
}
